nose_pynotify.py
setup.py
nose_pynotify.egg-info/PKG-INFO
nose_pynotify.egg-info/SOURCES.txt
nose_pynotify.egg-info/dependency_links.txt
nose_pynotify.egg-info/entry_points.txt
nose_pynotify.egg-info/top_level.txt