Metadata-Version: 1.0
Name: nose-pynotify
Version: 0.5
Summary: Plugin for nose to use pynotify for graphical notifications
Home-page: UNKNOWN
Author: Colin Drake
Author-email: colin.f.drake@gmail.com
License: BSD
Platform: UNKNOWN
